widgets/__init__.py
widgets/base/__init__.py
widgets/base/exceptions.py
widgets/base/helpers.py
widgets/base/io.py
widgets/base/resource.py
widgets/base/widget.py
widgets/cli/__init__.py
widgets/cli/main.py
widgets/st_base/resource.py
widgets/st_base/value.py
widgets/streamlit/__init__.py
widgets/streamlit/resource/__init__.py
widgets/streamlit/resource/columns.py
widgets/streamlit/resource/duplicator.py
widgets/streamlit/resource/expander.py
widgets/streamlit/resource/markdown.py
widgets/streamlit/resource/selector.py
widgets/streamlit/resource/files/__init__.py
widgets/streamlit/resource/files/base.py
widgets/streamlit/resource/files/dataframe.py
widgets/streamlit/resource/files/download_dataframe.py
widgets/streamlit/resource/values/checkbox.py
widgets/streamlit/resource/values/float.py
widgets/streamlit/resource/values/integer.py
widgets/streamlit/resource/values/multiselect.py
widgets/streamlit/resource/values/selectstring.py
widgets/streamlit/resource/values/slider.py
widgets/streamlit/resource/values/string.py
widgets/streamlit/resource/values/textarea.py
widgets/streamlit/widget/__init__.py
widgets/streamlit/widget/base.py
widgets/templates/source.py.j2
widgets/templates/streamlit_single.html.j2
widgets/templates/streamlit_single.py.j2
widgets/templates/streamlit_single_ga.html.j2
widgets_lib-2.7.7.data/data/templates/source.py.j2
widgets_lib-2.7.7.data/data/templates/streamlit_single.html.j2
widgets_lib-2.7.7.data/data/templates/streamlit_single.py.j2
widgets_lib-2.7.7.data/data/templates/streamlit_single_ga.html.j2
widgets_lib-2.7.7.dist-info/LICENSE
widgets_lib-2.7.7.dist-info/METADATA
widgets_lib-2.7.7.dist-info/WHEEL
widgets_lib-2.7.7.dist-info/entry_points.txt
widgets_lib-2.7.7.dist-info/top_level.txt
widgets_lib-2.7.7.dist-info/RECORD
