Metadata-Version: 2.1
Name: widgets-lib
Version: 2.7.7
Summary: Merging code and data in webpages
Author-email: Samuel Minot <sminot@fredhutch.org>
Project-URL: Homepage, https://github.com/FredHutch/widgets
Project-URL: Bug Tracker, https://github.com/FredHutch/widgets/issues
Classifier: Programming Language :: Python :: 3
Classifier: License :: OSI Approved :: MIT License
Classifier: Operating System :: OS Independent
Requires-Python: >=3.7
License-File: LICENSE
Requires-Dist: streamlit
Requires-Dist: pandas
Requires-Dist: jinja2
